CHANGES.txt
LICENSE.txt
MANIFEST.in
README.md
pyproject.toml
setup.cfg
setup.py
tox.ini
src/cert_utils/__init__.py
src/cert_utils/conditionals.py
src/cert_utils/convert.py
src/cert_utils/core.py
src/cert_utils/errors.py
src/cert_utils/letsencrypt_info.py
src/cert_utils/model.py
src/cert_utils/py.typed
src/cert_utils/utils.py
src/cert_utils.egg-info/PKG-INFO
src/cert_utils.egg-info/SOURCES.txt
src/cert_utils.egg-info/dependency_links.txt
src/cert_utils.egg-info/entry_points.txt
src/cert_utils.egg-info/not-zip-safe
src/cert_utils.egg-info/requires.txt
src/cert_utils.egg-info/top_level.txt
src/cert_utils/compat/__init__.py
src/cert_utils/compat/cryptography.py
src/cert_utils/compat/deprecated.py
src/cert_utils/compat/openssl.py
src/cert_utils/compat/pyopenssl.py
src/cert_utils/letsencrypt-certs/e7-cross.pem
src/cert_utils/letsencrypt-certs/e7.pem
src/cert_utils/letsencrypt-certs/e8-cross.pem
src/cert_utils/letsencrypt-certs/e8.pem
src/cert_utils/letsencrypt-certs/e9-cross.pem
src/cert_utils/letsencrypt-certs/e9.pem
src/cert_utils/letsencrypt-certs/isrg-root-x2-cross-signed.pem
src/cert_utils/letsencrypt-certs/isrg-root-x2.pem
src/cert_utils/letsencrypt-certs/isrgrootx1.pem
src/cert_utils/letsencrypt-certs/isrgrootx1.pkix
src/cert_utils/letsencrypt-certs/letsencrypt-stg-root-x1.pem
src/cert_utils/letsencrypt-certs/letsencrypt-stg-root-x2-signed-by-x1.pem
src/cert_utils/letsencrypt-certs/letsencrypt-stg-root-x2.pem
src/cert_utils/letsencrypt-certs/r12.pem
src/cert_utils/letsencrypt-certs/r13.pem
src/cert_utils/letsencrypt-certs/r14.pem
src/cert_utils/letsencrypt-certs/deprecated/e5-cross.pem
src/cert_utils/letsencrypt-certs/deprecated/e5.pem
src/cert_utils/letsencrypt-certs/deprecated/e6-cross.pem
src/cert_utils/letsencrypt-certs/deprecated/e6.pem
src/cert_utils/letsencrypt-certs/deprecated/fakeleintermediatex1.pem
src/cert_utils/letsencrypt-certs/deprecated/fakelerootx1.pem
src/cert_utils/letsencrypt-certs/deprecated/isrg-root-ocsp-x1.pem
src/cert_utils/letsencrypt-certs/deprecated/isrg-root-x1-cross-signed.pem
src/cert_utils/letsencrypt-certs/deprecated/lets-encrypt-e1.pem
src/cert_utils/letsencrypt-certs/deprecated/lets-encrypt-e2.pem
src/cert_utils/letsencrypt-certs/deprecated/lets-encrypt-r3-cross-signed.pem
