Metadata-Version: 2.4
Name: cert_utils
Version: 1.1.1
Summary: TLS/SSL Certiicate Utilities
Home-page: https://github.com/aptise/cert_utils
Author: Jonathan Vanasco
Author-email: jonathan@findmeon.com
License: MIT
Keywords: web
Classifier: Intended Audience :: Developers
Classifier: Programming Language :: Python
Classifier: Programming Language :: Python :: 3
Classifier: Programming Language :: Python :: 3.7
Classifier: Programming Language :: Python :: 3.8
Classifier: Programming Language :: Python :: 3.9
Classifier: Programming Language :: Python :: 3.10
Classifier: Programming Language :: Python :: 3.11
Classifier: Programming Language :: Python :: 3.12
Classifier: Programming Language :: Python :: 3.13
Requires-Python: >=3.7
License-File: LICENSE.txt
Requires-Dist: python-dateutil
Requires-Dist: psutil>=4.4.0
Requires-Dist: requests
Requires-Dist: typing_extensions
Provides-Extra: testing
Requires-Dist: certbot; extra == "testing"
Requires-Dist: cryptography>=42.0.0; extra == "testing"
Requires-Dist: josepy<3; extra == "testing"
Requires-Dist: mypy; extra == "testing"
Requires-Dist: pytest; extra == "testing"
Requires-Dist: types-psutil; extra == "testing"
Requires-Dist: types-python-dateutil; extra == "testing"
Requires-Dist: types-requests; extra == "testing"
Provides-Extra: josepy
Requires-Dist: josepy<3; extra == "josepy"
Dynamic: author
Dynamic: author-email
Dynamic: classifier
Dynamic: description
Dynamic: description-content-type
Dynamic: home-page
Dynamic: keywords
Dynamic: license
Dynamic: license-file
Dynamic: provides-extra
Dynamic: requires-dist
Dynamic: requires-python
Dynamic: summary
